odoo/addons/website_snippet_carousel_product/README.rst
odoo/addons/website_snippet_carousel_product/__init__.py
odoo/addons/website_snippet_carousel_product/__manifest__.py
odoo/addons/website_snippet_carousel_product/controllers/__init__.py
odoo/addons/website_snippet_carousel_product/controllers/website.py
odoo/addons/website_snippet_carousel_product/i18n/ca.po
odoo/addons/website_snippet_carousel_product/i18n/es.po
odoo/addons/website_snippet_carousel_product/i18n/fr.po
odoo/addons/website_snippet_carousel_product/i18n/nl.po
odoo/addons/website_snippet_carousel_product/i18n/website_snippet_carousel_product.pot
odoo/addons/website_snippet_carousel_product/readme/CONFIGURE.rst
odoo/addons/website_snippet_carousel_product/readme/CONTRIBUTORS.rst
odoo/addons/website_snippet_carousel_product/readme/DESCRIPTION.rst
odoo/addons/website_snippet_carousel_product/readme/ROADMAP.rst
odoo/addons/website_snippet_carousel_product/readme/USAGE.rst
odoo/addons/website_snippet_carousel_product/static/description/icon.png
odoo/addons/website_snippet_carousel_product/static/description/index.html
odoo/addons/website_snippet_carousel_product/static/src/js/s_product_carousel_frontend.js
odoo/addons/website_snippet_carousel_product/static/src/js/snippet.options.js
odoo/addons/website_snippet_carousel_product/static/src/scss/s_product_carousel.scss
odoo/addons/website_snippet_carousel_product/templates/assets.xml
odoo/addons/website_snippet_carousel_product/templates/snippet.xml
odoo13_addon_website_snippet_carousel_product-13.0.1.1.0.dist-info/METADATA
odoo13_addon_website_snippet_carousel_product-13.0.1.1.0.dist-info/WHEEL
odoo13_addon_website_snippet_carousel_product-13.0.1.1.0.dist-info/top_level.txt
odoo13_addon_website_snippet_carousel_product-13.0.1.1.0.dist-info/RECORD
